[
{"model_id": "116", "model_name": "80 2.0 E/L", "make_name": "AUDI", "make_id": "14", "year": "1996"},
{"model_id": "115", "model_name": "A4 1.8 TURBO FULL 20V", "make_name": "AUDI", "make_id": "14", "year": "1996"},
{"model_id": "119", "model_name": "A4 1.9 TDI", "make_name": "AUDI", "make_id": "14", "year": "1996"},
{"model_id": "126", "model_name": "A4 2.6 FULL", "make_name": "AUDI", "make_id": "14", "year": "1996"},
{"model_id": "125", "model_name": "A4 2.8 FULL V6 193 HP 4P.", "make_name": "AUDI", "make_id": "14", "year": "1996"}
]