[
{"model_id": "2024", "model_name": "116I 1.6 FULL 5P.", "make_name": "B.M.W.", "make_id": "20", "year": "2011"},
{"model_id": "2074", "model_name": "118I 2.0 EXTRA FULL 5P.", "make_name": "B.M.W.", "make_id": "20", "year": "2011"},
{"model_id": "2025", "model_name": "120 I 2.0 CABRIOLET FULL", "make_name": "B.M.W.", "make_id": "20", "year": "2011"},
{"model_id": "2042", "model_name": "120 I 2.0 COUPE EXTRA FULL 2P.", "make_name": "B.M.W.", "make_id": "20", "year": "2011"},
{"model_id": "2006", "model_name": "120 I 2.0 EXTRA FULL AUT.", "make_name": "B.M.W.", "make_id": "20", "year": "2011"},
{"model_id": "2005", "model_name": "120 I 2.0 FULL", "make_name": "B.M.W.", "make_id": "20", "year": "2011"},
{"model_id": "2026", "model_name": "125 I 2.5 COUPE EXTRA FULL", "make_name": "B.M.W.", "make_id": "20", "year": "2011"},
{"model_id": "2029", "model_name": "135 I 3.0 CABRIO EXTRA FULL 2P.", "make_name": "B.M.W.", "make_id": "20", "year": "2011"},
{"model_id": "2124", "model_name": "135 I 3.0 M COUPE EXTRA FULL 2P.", "make_name": "B.M.W.", "make_id": "20", "year": "2011"},
{"model_id": "2110", "model_name": "316 I FULL 4P. (E90)", "make_name": "B.M.W.", "make_id": "20", "year": "2011"},
{"model_id": "121", "model_name": "318 I", "make_name": "B.M.W.", "make_id": "20", "year": "2011"},
{"model_id": "144", "model_name": "320 I", "make_name": "B.M.W.", "make_id": "20", "year": "2011"},
{"model_id": "2021", "model_name": "320 I 2.0 CA CABRIO EXTRA FULL AUT. 2P. (E93)", "make_name": "B.M.W.", "make_id": "20", "year": "2011"},
{"model_id": "2147", "model_name": "320 I COUPE FULL 2P. (E92)", "make_name": "B.M.W.", "make_id": "20", "year": "2011"},
{"model_id": "311", "model_name": "325 I CABRIO CONVERTIBLE", "make_name": "B.M.W.", "make_id": "20", "year": "2011"},
{"model_id": "2008", "model_name": "325 I FULL 4P. AUT. (E90)", "make_name": "B.M.W.", "make_id": "20", "year": "2011"},
{"model_id": "2142", "model_name": "325 I FULL, IDRIVE 2P. AUT. (E92)", "make_name": "B.M.W.", "make_id": "20", "year": "2011"},
{"model_id": "2108", "model_name": "328I FULL 4P. AUT. (E90)", "make_name": "B.M.W.", "make_id": "20", "year": "2011"},
{"model_id": "1002", "model_name": "330 I/CI", "make_name": "B.M.W.", "make_id": "20", "year": "2011"},
{"model_id": "562", "model_name": "523 I", "make_name": "B.M.W.", "make_id": "20", "year": "2011"},
{"model_id": "356", "model_name": "528I N20 FULL 4P. AUT. (F10)", "make_name": "B.M.W.", "make_id": "20", "year": "2011"},
{"model_id": "2119", "model_name": "535I FULL 4P. AUT. (F10)", "make_name": "B.M.W.", "make_id": "20", "year": "2011"},
{"model_id": "2061", "model_name": "F 650 GS BICILINDRICO", "make_name": "B.M.W.", "make_id": "20", "year": "2011"},
{"model_id": "2060", "model_name": "F 800 GS", "make_name": "B.M.W.", "make_id": "20", "year": "2011"},
{"model_id": "2064", "model_name": "F 800 ST", "make_name": "B.M.W.", "make_id": "20", "year": "2011"},
{"model_id": "2082", "model_name": "G 450 X", "make_name": "B.M.W.", "make_id": "20", "year": "2011"},
{"model_id": "2062", "model_name": "G 650 GS MONOCILINDRICO", "make_name": "B.M.W.", "make_id": "20", "year": "2011"},
{"model_id": "2063", "model_name": "G 650 XCOUNTRY", "make_name": "B.M.W.", "make_id": "20", "year": "2011"},
{"model_id": "2065", "model_name": "K 1200 RS", "make_name": "B.M.W.", "make_id": "20", "year": "2011"},
{"model_id": "2071", "model_name": "K 1300 GT", "make_name": "B.M.W.", "make_id": "20", "year": "2011"},
{"model_id": "2067", "model_name": "K 1300 R", "make_name": "B.M.W.", "make_id": "20", "year": "2011"},
{"model_id": "2069", "model_name": "K 1300 S", "make_name": "B.M.W.", "make_id": "20", "year": "2011"},
{"model_id": "2085", "model_name": "K 1600 GT", "make_name": "B.M.W.", "make_id": "20", "year": "2011"},
{"model_id": "2059", "model_name": "R 1200 GS", "make_name": "B.M.W.", "make_id": "20", "year": "2011"},
{"model_id": "2020", "model_name": "R 1200 GS ADVENTURE", "make_name": "B.M.W.", "make_id": "20", "year": "2011"},
{"model_id": "2066", "model_name": "R 1200 R", "make_name": "B.M.W.", "make_id": "20", "year": "2011"},
{"model_id": "2070", "model_name": "R 1200 RT", "make_name": "B.M.W.", "make_id": "20", "year": "2011"},
{"model_id": "2068", "model_name": "S 1000 RR", "make_name": "B.M.W.", "make_id": "20", "year": "2011"},
{"model_id": "2073", "model_name": "X1 18I 2.0 EXTRA FULL 5P.", "make_name": "B.M.W.", "make_id": "20", "year": "2011"},
{"model_id": "2041", "model_name": "X1 18I 2.0 EXTRA FULL 5P. AUT.", "make_name": "B.M.W.", "make_id": "20", "year": "2011"},
{"model_id": "2120", "model_name": "X1 18I 2.0 EXTRA FULL, TECHO 5P.", "make_name": "B.M.W.", "make_id": "20", "year": "2011"},
{"model_id": "2160", "model_name": "X1 18I 2.0 EXTRA FULL, TECHO, IDRIVE 5P.", "make_name": "B.M.W.", "make_id": "20", "year": "2011"},
{"model_id": "2036", "model_name": "X1 3.0 28I V6 258 HP 4X4 EXTRA FULL 5P. AUT.", "make_name": "B.M.W.", "make_id": "20", "year": "2011"},
{"model_id": "2040", "model_name": "X1 3.0 XDRIVE 25I 4X4 EXTRA FULL", "make_name": "B.M.W.", "make_id": "20", "year": "2011"},
{"model_id": "2111", "model_name": "X3 2.0 XDRIVE 20D TURBO DIESEL 184 HP 4X4 FULL 5P.", "make_name": "B.M.W.", "make_id": "20", "year": "2011"},
{"model_id": "2054", "model_name": "X3 3.0 28I XDRIVE 4X4 FULL", "make_name": "B.M.W.", "make_id": "20", "year": "2011"},
{"model_id": "2048", "model_name": "X3 3.0 35I XDRIVE 4X4 EXTRA FULL", "make_name": "B.M.W.", "make_id": "20", "year": "2011"},
{"model_id": "2031", "model_name": "X6 3.0 35I XDRIVE EXTRA FULL", "make_name": "B.M.W.", "make_id": "20", "year": "2011"},
{"model_id": "2053", "model_name": "Z4 23I S-DRIVE ROADSTER TECHO DURO RETRACTIL", "make_name": "B.M.W.", "make_id": "20", "year": "2011"}
]