[
{"model_id": "450", "model_name": "CINCUECENTO", "make_name": "FIAT", "make_id": "31", "year": "1995"},
{"model_id": "261", "model_name": "CROMA 2.0 FULL", "make_name": "FIAT", "make_id": "31", "year": "1995"},
{"model_id": "454", "model_name": "CROMA 2.0 FULL", "make_name": "FIAT", "make_id": "31", "year": "1995"},
{"model_id": "455", "model_name": "CROMA 2.5 TD", "make_name": "FIAT", "make_id": "31", "year": "1995"},
{"model_id": "265", "model_name": "DUNA CS/CL/SL/CSL", "make_name": "FIAT", "make_id": "31", "year": "1995"},
{"model_id": "458", "model_name": "DUNA CS/CL/SL/CSL", "make_name": "FIAT", "make_id": "31", "year": "1995"},
{"model_id": "461", "model_name": "DUNA CS/CL/SL/CSL", "make_name": "FIAT", "make_id": "31", "year": "1995"},
{"model_id": "277", "model_name": "DUNA CS/DS/CSL/SDL/SDR 1.7 DIESEL", "make_name": "FIAT", "make_id": "31", "year": "1995"},
{"model_id": "408", "model_name": "DUNA CS/DS/CSL/SDL/SDR 1.7 DIESEL", "make_name": "FIAT", "make_id": "31", "year": "1995"},
{"model_id": "459", "model_name": "DUNA CS/DS/CSL/SDL/SDR 1.7 DIESEL", "make_name": "FIAT", "make_id": "31", "year": "1995"},
{"model_id": "460", "model_name": "DUNA CS/DS/CSL/SDL/SDR 1.7 DIESEL", "make_name": "FIAT", "make_id": "31", "year": "1995"},
{"model_id": "301", "model_name": "ELBA CSL 1.6 I.E.", "make_name": "FIAT", "make_id": "31", "year": "1995"},
{"model_id": "462", "model_name": "ELBA CSL 1.6 I.E.", "make_name": "FIAT", "make_id": "31", "year": "1995"},
{"model_id": "463", "model_name": "ELBA INNOCENTI 1.7 D", "make_name": "FIAT", "make_id": "31", "year": "1995"},
{"model_id": "425", "model_name": "PANDA", "make_name": "FIAT", "make_id": "31", "year": "1995"},
{"model_id": "427", "model_name": "PANORAMA", "make_name": "FIAT", "make_id": "31", "year": "1995"},
{"model_id": "466", "model_name": "PANORAMA", "make_name": "FIAT", "make_id": "31", "year": "1995"},
{"model_id": "467", "model_name": "PANORAMA", "make_name": "FIAT", "make_id": "31", "year": "1995"},
{"model_id": "430", "model_name": "PREMIO CSL 1.6", "make_name": "FIAT", "make_id": "31", "year": "1995"},
{"model_id": "344", "model_name": "PREMIO S/SL/CS", "make_name": "FIAT", "make_id": "31", "year": "1995"},
{"model_id": "1001", "model_name": "PREMIO S/SL/CS", "make_name": "FIAT", "make_id": "31", "year": "1995"},
{"model_id": "494", "model_name": "PUNTO 55 1.1", "make_name": "FIAT", "make_id": "31", "year": "1995"},
{"model_id": "481", "model_name": "PUNTO 55 1.6", "make_name": "FIAT", "make_id": "31", "year": "1995"},
{"model_id": "432", "model_name": "SPAZIO TIPO 1400", "make_name": "FIAT", "make_id": "31", "year": "1995"},
{"model_id": "363", "model_name": "TEMPRA 2.0 I.E.", "make_name": "FIAT", "make_id": "31", "year": "1995"},
{"model_id": "364", "model_name": "TEMPRA 2.0 I.E.", "make_name": "FIAT", "make_id": "31", "year": "1995"},
{"model_id": "435", "model_name": "TEMPRA SEDAN/SW TDS", "make_name": "FIAT", "make_id": "31", "year": "1995"},
{"model_id": "438", "model_name": "TIPO SX 1.6", "make_name": "FIAT", "make_id": "31", "year": "1995"},
{"model_id": "365", "model_name": "UNO (S-CL-CS-FIRE-TOP)", "make_name": "FIAT", "make_id": "31", "year": "1995"},
{"model_id": "452", "model_name": "UNO (S-CL-CS-FIRE-TOP)", "make_name": "FIAT", "make_id": "31", "year": "1995"},
{"model_id": "443", "model_name": "UNO D 1.7", "make_name": "FIAT", "make_id": "31", "year": "1995"},
{"model_id": "373", "model_name": "UNO D/SD", "make_name": "FIAT", "make_id": "31", "year": "1995"},
{"model_id": "444", "model_name": "UNO SCR 1.6", "make_name": "FIAT", "make_id": "31", "year": "1995"},
{"model_id": "445", "model_name": "UNO SX 1.5", "make_name": "FIAT", "make_id": "31", "year": "1995"}
]