[
{"model_id": "57", "model_name": "H2 1.5T ELITE FULL, 6ABAG, ABS, CUERO 5P. AUT.", "make_name": "G.W.M.", "make_id": "161", "year": "2016"},
{"model_id": "36", "model_name": "HAVAL H6 CITY 1.5 FULL, 2ABAG, ABS+EBD, FAROS, LLANTAS, 5P.", "make_name": "G.W.M.", "make_id": "161", "year": "2016"},
{"model_id": "38", "model_name": "HAVAL H6 CITY 2.4 FULL, 2ABAG, ABS+EBD, FAROS, LLANTAS 5P.", "make_name": "G.W.M.", "make_id": "161", "year": "2016"},
{"model_id": "56", "model_name": "HAVAL M4 1.5 VVT FULL, 2ABAG, ABS, FAROS, LLANTAS", "make_name": "G.W.M.", "make_id": "161", "year": "2016"},
{"model_id": "58", "model_name": "VOLEEX C30 1.5 VVT INTELLIGENT EXTRA FULL 4P.", "make_name": "G.W.M.", "make_id": "161", "year": "2016"},
{"model_id": "59", "model_name": "VOLEEX C30 1.5 VVT INTELLIGENT EXTRA FULL 4P. AUT", "make_name": "G.W.M.", "make_id": "161", "year": "2016"},
{"model_id": "51", "model_name": "WINGLE 4X2 PICK UP 2.8 DIESEL C. RAIL FULL,LLAN,CUERO,2ABAG,ABS", "make_name": "G.W.M.", "make_id": "161", "year": "2016"},
{"model_id": "47", "model_name": "WINGLE 5 4X2 DOBLE CABINA 2.4 LUXURY FULL, 2ABAG, ABS", "make_name": "G.W.M.", "make_id": "161", "year": "2016"},
{"model_id": "48", "model_name": "WINGLE 5 4X2 DOBLE CABINA 2.4 S.LUXURY FULL,2ABAG,ABS,CUERO", "make_name": "G.W.M.", "make_id": "161", "year": "2016"},
{"model_id": "50", "model_name": "WINGLE 5 4X4 DOBLE CABINA 2.4 S.LUXURY FULL,2ABAG,ABS,CUERO", "make_name": "G.W.M.", "make_id": "161", "year": "2016"},
{"model_id": "44", "model_name": "WINGLE 5E 4X2 DOBLE CABINA 2.4 SUPER LUXARY EXTRA FULL, CUERO", "make_name": "G.W.M.", "make_id": "161", "year": "2016"},
{"model_id": "45", "model_name": "WINGLE 5E 4X4 DOBLE CABINA 2.4 SUPER LUXARY EXTRA FULL, CUERO", "make_name": "G.W.M.", "make_id": "161", "year": "2016"},
{"model_id": "54", "model_name": "WINGLE 5E 4X4 DOBLE CABINA 2.8 DIESEL SUP.LUXARY EX.FULL,CUE", "make_name": "G.W.M.", "make_id": "161", "year": "2016"}
]