[
{"model_id": "2007", "model_name": "GRAND CHEROKEE LAREDO 3.7 V6", "make_name": "JEEP", "make_id": "40", "year": "2006"},
{"model_id": "2010", "model_name": "GRAND CHEROKEE LIMITED 4.7 V8 4X4", "make_name": "JEEP", "make_id": "40", "year": "2006"},
{"model_id": "2011", "model_name": "GRAND CHEROKEE LIMITED 5.7 HEMI V8 4X4", "make_name": "JEEP", "make_id": "40", "year": "2006"},
{"model_id": "2019", "model_name": "LIBERTY 2.8 CRD T.DIESEL 4X4 FULL 5P.", "make_name": "JEEP", "make_id": "40", "year": "2006"},
{"model_id": "2014", "model_name": "WRANGLER SPORT 3.8 V6 4X4 EXTRA FULL 4P. (RUBICOM)", "make_name": "JEEP", "make_id": "40", "year": "2006"}
]