[
{"model_id": "1001", "model_name": "DISCOVERY TD5 S TDI TURBO DIESEL EXTRA FULL 5CIL", "make_name": "LAND ROVER", "make_id": "43", "year": "2003"},
{"model_id": "2020", "model_name": "DISCOVERY TD5 S TDI TURBO DIESEL EXTRA FULL 5CIL AUT.", "make_name": "LAND ROVER", "make_id": "43", "year": "2003"},
{"model_id": "147", "model_name": "FREELANDER 2.0 SE DI DIESEL", "make_name": "LAND ROVER", "make_id": "43", "year": "2003"},
{"model_id": "2005", "model_name": "FREELANDER 2.5 TD4 TURBO DIESEL", "make_name": "LAND ROVER", "make_id": "43", "year": "2003"},
{"model_id": "2009", "model_name": "FREELANDER 2.5 V6", "make_name": "LAND ROVER", "make_id": "43", "year": "2003"}
]