[
{"model_id": "116", "model_name": "190 D 2.5 DIESEL", "make_name": "MERCEDES BENZ", "make_id": "47", "year": "1993"},
{"model_id": "131", "model_name": "190 E 1.8", "make_name": "MERCEDES BENZ", "make_id": "47", "year": "1993"},
{"model_id": "134", "model_name": "190 E 1.8", "make_name": "MERCEDES BENZ", "make_id": "47", "year": "1993"},
{"model_id": "138", "model_name": "190 E 2.0", "make_name": "MERCEDES BENZ", "make_id": "47", "year": "1993"},
{"model_id": "145", "model_name": "190 E 2.3", "make_name": "MERCEDES BENZ", "make_id": "47", "year": "1993"},
{"model_id": "149", "model_name": "190 E 2.6", "make_name": "MERCEDES BENZ", "make_id": "47", "year": "1993"},
{"model_id": "162", "model_name": "200 D", "make_name": "MERCEDES BENZ", "make_id": "47", "year": "1993"},
{"model_id": "432", "model_name": "200 D", "make_name": "MERCEDES BENZ", "make_id": "47", "year": "1993"},
{"model_id": "433", "model_name": "200 D", "make_name": "MERCEDES BENZ", "make_id": "47", "year": "1993"},
{"model_id": "434", "model_name": "200 D", "make_name": "MERCEDES BENZ", "make_id": "47", "year": "1993"},
{"model_id": "153", "model_name": "200 E", "make_name": "MERCEDES BENZ", "make_id": "47", "year": "1993"},
{"model_id": "422", "model_name": "200 E", "make_name": "MERCEDES BENZ", "make_id": "47", "year": "1993"},
{"model_id": "185", "model_name": "230 E", "make_name": "MERCEDES BENZ", "make_id": "47", "year": "1993"},
{"model_id": "439", "model_name": "230 E", "make_name": "MERCEDES BENZ", "make_id": "47", "year": "1993"},
{"model_id": "234", "model_name": "250 D", "make_name": "MERCEDES BENZ", "make_id": "47", "year": "1993"},
{"model_id": "442", "model_name": "250 D", "make_name": "MERCEDES BENZ", "make_id": "47", "year": "1993"},
{"model_id": "443", "model_name": "250 D", "make_name": "MERCEDES BENZ", "make_id": "47", "year": "1993"},
{"model_id": "240", "model_name": "250 TD", "make_name": "MERCEDES BENZ", "make_id": "47", "year": "1993"},
{"model_id": "290", "model_name": "280 TE", "make_name": "MERCEDES BENZ", "make_id": "47", "year": "1993"},
{"model_id": "444", "model_name": "280 TE", "make_name": "MERCEDES BENZ", "make_id": "47", "year": "1993"},
{"model_id": "445", "model_name": "300 CD TURBO DIESEL", "make_name": "MERCEDES BENZ", "make_id": "47", "year": "1993"},
{"model_id": "446", "model_name": "300 CE COUPE 12V/24V CABRIOLET", "make_name": "MERCEDES BENZ", "make_id": "47", "year": "1993"},
{"model_id": "302", "model_name": "300 D", "make_name": "MERCEDES BENZ", "make_id": "47", "year": "1993"},
{"model_id": "334", "model_name": "300 LE 24V CABRIOLET", "make_name": "MERCEDES BENZ", "make_id": "47", "year": "1993"},
{"model_id": "344", "model_name": "300 SD TURBO", "make_name": "MERCEDES BENZ", "make_id": "47", "year": "1993"},
{"model_id": "345", "model_name": "300 SE/SEL", "make_name": "MERCEDES BENZ", "make_id": "47", "year": "1993"},
{"model_id": "347", "model_name": "300 SE/SEL", "make_name": "MERCEDES BENZ", "make_id": "47", "year": "1993"},
{"model_id": "356", "model_name": "300 SL 24V ROADSTER/COUPE", "make_name": "MERCEDES BENZ", "make_id": "47", "year": "1993"},
{"model_id": "358", "model_name": "300 SL 24V ROADSTER/COUPE", "make_name": "MERCEDES BENZ", "make_id": "47", "year": "1993"},
{"model_id": "316", "model_name": "300 TD", "make_name": "MERCEDES BENZ", "make_id": "47", "year": "1993"},
{"model_id": "395", "model_name": "320 CE", "make_name": "MERCEDES BENZ", "make_id": "47", "year": "1993"},
{"model_id": "418", "model_name": "500 SL CABRIO ROADSTER", "make_name": "MERCEDES BENZ", "make_id": "47", "year": "1993"},
{"model_id": "2241", "model_name": "600 SL CABRIO", "make_name": "MERCEDES BENZ", "make_id": "47", "year": "1993"},
{"model_id": "436", "model_name": "C 220", "make_name": "MERCEDES BENZ", "make_id": "47", "year": "1993"},
{"model_id": "440", "model_name": "C 250 D", "make_name": "MERCEDES BENZ", "make_id": "47", "year": "1993"},
{"model_id": "2253", "model_name": "E 200 DIESEL (W 210)", "make_name": "MERCEDES BENZ", "make_id": "47", "year": "1993"},
{"model_id": "441", "model_name": "E 250 D", "make_name": "MERCEDES BENZ", "make_id": "47", "year": "1993"},
{"model_id": "469", "model_name": "E 300 TURBO DIESEL", "make_name": "MERCEDES BENZ", "make_id": "47", "year": "1993"},
{"model_id": "2052", "model_name": "S 300 BERLINA", "make_name": "MERCEDES BENZ", "make_id": "47", "year": "1993"},
{"model_id": "2062", "model_name": "S 320 BERLINA (W 140)", "make_name": "MERCEDES BENZ", "make_id": "47", "year": "1993"},
{"model_id": "459", "model_name": "SL 320 COUPE", "make_name": "MERCEDES BENZ", "make_id": "47", "year": "1993"},
{"model_id": "2219", "model_name": "SL 500 ROADSTER COUP\u00c9 (W 230)(W 170)", "make_name": "MERCEDES BENZ", "make_id": "47", "year": "1993"}
]