[
{"model_id": "5", "model_name": "FALCON 125", "make_name": "UM", "make_id": "258", "year": "2012"},
{"model_id": "7", "model_name": "FASTWIND 200", "make_name": "UM", "make_id": "258", "year": "2012"},
{"model_id": "4", "model_name": "MAX 125", "make_name": "UM", "make_id": "258", "year": "2012"},
{"model_id": "3", "model_name": "NITROX 125", "make_name": "UM", "make_id": "258", "year": "2012"},
{"model_id": "2", "model_name": "XTREET 200", "make_name": "UM", "make_id": "258", "year": "2012"},
{"model_id": "1", "model_name": "XTREET 230", "make_name": "UM", "make_id": "258", "year": "2012"}
]